MANIFEST.in
README.rst
setup.py
django_icons_twitterjoy.egg-info/PKG-INFO
django_icons_twitterjoy.egg-info/SOURCES.txt
django_icons_twitterjoy.egg-info/dependency_links.txt
django_icons_twitterjoy.egg-info/requires.txt
django_icons_twitterjoy.egg-info/top_level.txt
icons_twitterjoy/__init__.py
icons_twitterjoy/models.py
icons_twitterjoy/static/icons/.noremove
icons_twitterjoy/static/icons/twitterjoy/1/preview.jpg
icons_twitterjoy/static/icons/twitterjoy/1/readme.txt
icons_twitterjoy/static/icons/twitterjoy/1/ICNS/01_128x128.icns
icons_twitterjoy/static/icons/twitterjoy/1/ICNS/02_128x128.icns
icons_twitterjoy/static/icons/twitterjoy/1/ICNS/03_128x128.icns
icons_twitterjoy/static/icons/twitterjoy/1/ICO/01_128x128.ico
icons_twitterjoy/static/icons/twitterjoy/1/ICO/02_128x128.ico
icons_twitterjoy/static/icons/twitterjoy/1/ICO/03_128x128.ico
icons_twitterjoy/static/icons/twitterjoy/1/PNG/01_128x128.png
icons_twitterjoy/static/icons/twitterjoy/1/PNG/01_24x24.png
icons_twitterjoy/static/icons/twitterjoy/1/PNG/01_32x32.png
icons_twitterjoy/static/icons/twitterjoy/1/PNG/01_48x48.png
icons_twitterjoy/static/icons/twitterjoy/1/PNG/01_64x64.png
icons_twitterjoy/static/icons/twitterjoy/1/PNG/01_96x96.png
icons_twitterjoy/static/icons/twitterjoy/1/PNG/02_128x128.png
icons_twitterjoy/static/icons/twitterjoy/1/PNG/02_24x24.png
icons_twitterjoy/static/icons/twitterjoy/1/PNG/02_32x32.png
icons_twitterjoy/static/icons/twitterjoy/1/PNG/02_48x48.png
icons_twitterjoy/static/icons/twitterjoy/1/PNG/02_64x64.png
icons_twitterjoy/static/icons/twitterjoy/1/PNG/02_96x96.png
icons_twitterjoy/static/icons/twitterjoy/1/PNG/03_128x128.png
icons_twitterjoy/static/icons/twitterjoy/1/PNG/03_24x24.png
icons_twitterjoy/static/icons/twitterjoy/1/PNG/03_32x32.png
icons_twitterjoy/static/icons/twitterjoy/1/PNG/03_48x48.png
icons_twitterjoy/static/icons/twitterjoy/1/PNG/03_64x64.png
icons_twitterjoy/static/icons/twitterjoy/1/PNG/03_96x96.png
icons_twitterjoy/static/icons/twitterjoy/2/preview.jpg
icons_twitterjoy/static/icons/twitterjoy/2/readme.txt
icons_twitterjoy/static/icons/twitterjoy/2/ICNS/01_128x128.icns
icons_twitterjoy/static/icons/twitterjoy/2/ICNS/02_128x128.icns
