Metadata-Version: 1.0
Name: django-icons-twitterjoy
Version: 1.0
Summary: twitterjoy icons pack for django.contrib.staticfiles
Home-page: http://bitbucket.org/kmike/django-icons/
Author: Mikhail Korobov
Author-email: kmike84@gmail.com
License: MIT license
Platform: UNKNOWN
Classifier: Development Status :: 5 - Production/Stable
Classifier: Framework :: Django
Classifier: Intended Audience :: Developers
Classifier: License :: OSI Approved :: MIT License
Classifier: Programming Language :: Python
Classifier: Topic :: Multimedia :: Graphics
Classifier: Topic :: Software Development :: Libraries :: Python Modules
